.gitignore
MANIFEST.in
README.rst
setup.cfg
setup.py
docs/HISTORY.txt
raptus/__init__.py
raptus.rolefield.egg-info/PKG-INFO
raptus.rolefield.egg-info/SOURCES.txt
raptus.rolefield.egg-info/dependency_links.txt
raptus.rolefield.egg-info/entry_points.txt
raptus.rolefield.egg-info/namespace_packages.txt
raptus.rolefield.egg-info/not-zip-safe
raptus.rolefield.egg-info/requires.txt
raptus.rolefield.egg-info/top_level.txt
raptus/rolefield/__init__.py
raptus/rolefield/configure.zcml
raptus/rolefield/fields.py
raptus/rolefield/i18n/raptus.rolefield-de.mo
raptus/rolefield/i18n/raptus.rolefield-de.po
raptus/rolefield/i18n/raptus.rolefield-fr.mo
raptus/rolefield/i18n/raptus.rolefield-fr.po
raptus/rolefield/i18n/raptus.rolefield.pot