Metadata-Version: 1.1
Name: raptus.rolefield
Version: 1.1
Summary: Provides two archetypes fields which assign local roles to one or multiple users
Home-page: https://github.com/Raptus/raptus.rolefield
Author: Raptus AG
Author-email: dev@raptus.com
License: GPL
Platform: UNKNOWN
Classifier: Programming Language :: Python
Classifier: Topic :: Software Development :: Libraries :: Python Modules
